cqh_file
